catkin_tools_document/__init__.py
catkin_tools_document/builders.py
catkin_tools_document/cli.py
catkin_tools_document/document.py
catkin_tools_document/doxygen.py
catkin_tools_document/intersphinx.py
catkin_tools_document/messages.py
catkin_tools_document/util.py
catkin_tools_document/external/cppreference-doxygen-web.tag.xml
catkin_tools_document/spaces/__init__.py
catkin_tools_document/spaces/docs.py
catkin_tools_document-0.5.2.dist-info/LICENSE
catkin_tools_document-0.5.2.dist-info/METADATA
catkin_tools_document-0.5.2.dist-info/WHEEL
catkin_tools_document-0.5.2.dist-info/entry_points.txt
catkin_tools_document-0.5.2.dist-info/top_level.txt
catkin_tools_document-0.5.2.dist-info/RECORD
